Workbook

Sheet Balance Sheet
A1: Balance Sheet
C2: Forecast Period
A3: end of | B3: Year 0 | C3: ='[1]IS Cash Flow'!C3 -> 1 | D3: ='[1]IS Cash Flow'!D3 -> 2 | E3: ='[1]IS Cash Flow'!E3 -> 3 | F3: ='[1]IS Cash Flow'!F3 -> 4 | G3: ='[1]IS Cash Flow'!G3 -> 5 | H3: ='[1]IS Cash Flow'!H3 -> 6 | I3: ='[1]IS Cash Flow'!I3 -> 7
A4: ASSETS
A5: Current Assets
A6: Cash at Bank | B6: 7500 | C6: ='[1]IS Cash Flow'!C57 -> 17606.456 | D6: ='[1]IS Cash Flow'!D57 -> 29925.342 | E6: ='[1]IS Cash Flow'!E57 -> 44616.535 | F6: ='[1]IS Cash Flow'!F57 -> 61849.387 | G6: ='[1]IS Cash Flow'!G57 -> 80824.829 | H6: ='[1]IS Cash Flow'!H57 -> 100357.8 | I6: ='[1]IS Cash Flow'!I57 -> 120307.5
A8: Accounts Receivable | B8: 12500 | C8: ='[1]IS Cash Flow'!C4/C9 -> 13125 | D8: ='[1]IS Cash Flow'!D4/D9 -> 13781.25 | E8: ='[1]IS Cash Flow'!E4/E9 -> 14470.313 | F8: ='[1]IS Cash Flow'!F4/F9 -> 15193.828 | G8: ='[1]IS Cash Flow'!G4/G9 -> 15649.643 | H8: ='[1]IS Cash Flow'!H4/H9 -> 15962.636 | I8: ='[1]IS Cash Flow'!I4/I9 -> 16281.889
A9: AR turnover | B9: ='[1]IS Cash Flow'!B4/'[1]Bal Sheet'!B8 -> 8.940384 | C9: =B9 -> 8.940384 | D9: =C9 -> 8.940384 | E9: =D9 -> 8.940384 | F9: =E9 -> 8.940384 | G9: =F9 -> 8.940384 | H9: =G9 -> 8.940384 | I9: =H9 -> 8.940384
A11: Total Current Assets | B11: =SUM(B6,B8) -> 20000 | C11: =SUM(C6,C8) -> 30731.456 | D11: =SUM(D6,D8) -> 43706.592 | E11: =SUM(E6,E8) -> 59086.848 | F11: =SUM(F6,F8) -> 77043.216 | G11: =SUM(G6,G8) -> 96474.472 | H11: =SUM(H6,H8) -> 116320.43 | I11: =SUM(I6,I8) -> 136589.39
A13: Fixed Assets
A14: Gross PP&E | B14: 30000 | C14: =B14-'[1]IS Cash Flow'!C45 -> 38213.978 | D14: =C14-'[1]IS Cash Flow'!D45 -> 46838.654 | E14: =D14-'[1]IS Cash Flow'!E45 -> 55894.565 | F14: =E14-'[1]IS Cash Flow'!F45 -> 65403.271 | G14: =F14-'[1]IS Cash Flow'!G45 -> 75197.238 | H14: =G14-'[1]IS Cash Flow'!H45 -> 85187.085 | I14: =H14-'[1]IS Cash Flow'!I45 -> 95376.728
A15: Less: Accumulated D&A | B15: 0 | C15: =-'[1]IS Cash Flow'!C13+B15 -> -2625 | D15: =-'[1]IS Cash Flow'!D13+C15 -> -5381.25 | E15: =-'[1]IS Cash Flow'!E13+D15 -> -8275.3125 | F15: =-'[1]IS Cash Flow'!F13+E15 -> -11314.078 | G15: =-'[1]IS Cash Flow'!G13+F15 -> -14444.007 | H15: =-'[1]IS Cash Flow'!H13+G15 -> -17636.534 | I15: =-'[1]IS Cash Flow'!I13+H15 -> -20892.912
A16: Net PP&E (net of D&A) | B16: =SUM(B14:B15) -> 30000 | C16: =SUM(C14:C15) -> 35588.978 | D16: =SUM(D14:D15) -> 41457.404 | E16: =SUM(E14:E15) -> 47619.253 | F16: =SUM(F14:F15) -> 54089.193 | G16: =SUM(G14:G15) -> 60753.232 | H16: =SUM(H14:H15) -> 67550.551 | I16: =SUM(I14:I15) -> 74483.817
A18: TOTAL ASSETS | B18: =B16+B11 -> 50000 | C18: =C16+C11 -> 66320.434 | D18: =D16+D11 -> 85163.996 | E18: =E16+E11 -> 106706.1 | F18: =F16+F11 -> 131132.41 | G18: =G16+G11 -> 157227.7 | H18: =H16+H11 -> 183870.98 | I18: =I16+I11 -> 211073.21
A20: LIABILITIES
A21: Current Liabilities
A22: Accounts Payable
A23: AP turnover
A25: Total Current Liabilities | B25: =SUM(B22) -> 0 | C25: =SUM(C22) -> 0 | D25: =SUM(D22) -> 0 | E25: =SUM(E22) -> 0 | F25: =SUM(F22) -> 0 | G25: =SUM(G22) -> 0 | H25: =SUM(H22) -> 0 | I25: =SUM(I22) -> 0
A27: Long Term Liabilities
A28: Long Term Debt | B28: 30000 | C28: =B28+'[1]IS Cash Flow'!C51-'[1]IS Cash Flow'!C52 -> 30000 | D28: =C28+'[1]IS Cash Flow'!D51-'[1]IS Cash Flow'!D52 -> 30000 | E28: =D28+'[1]IS Cash Flow'!E51-'[1]IS Cash Flow'!E52 -> 30000 | F28: =E28+'[1]IS Cash Flow'!F51-'[1]IS Cash Flow'!F52 -> 30000 | G28: =F28+'[1]IS Cash Flow'!G51-'[1]IS Cash Flow'!G52 -> 30000 | H28: =G28+'[1]IS Cash Flow'!H51-'[1]IS Cash Flow'!H52 -> 30000 | I28: =H28+'[1]IS Cash Flow'!I51-'[1]IS Cash Flow'!I52 -> 30000
A29: Total Long Term Liabilities | B29: =SUM(B28) -> 30000 | C29: =SUM(C28) -> 30000 | D29: =SUM(D28) -> 30000 | E29: =SUM(E28) -> 30000 | F29: =SUM(F28) -> 30000 | G29: =SUM(G28) -> 30000 | H29: =SUM(H28) -> 30000 | I29: =SUM(I28) -> 30000
A31: EQUITY
A32: Owner's Funds | B32: 20000 | C32: =B32 -> 20000 | D32: =C32 -> 20000 | E32: =D32 -> 20000 | F32: =E32 -> 20000 | G32: =F32 -> 20000 | H32: =G32 -> 20000 | I32: =H32 -> 20000
A33: Retained Earnings | B33: 0 | C33: =B33+'[1]IS Cash Flow'!C27 -> 16320.434 | D33: =C33+'[1]IS Cash Flow'!D27 -> 35163.996 | E33: =D33+'[1]IS Cash Flow'!E27 -> 56706.1 | F33: =E33+'[1]IS Cash Flow'!F27 -> 81132.409 | G33: =F33+'[1]IS Cash Flow'!G27 -> 107227.7 | H33: =G33+'[1]IS Cash Flow'!H27 -> 133870.98 | I33: =H33+'[1]IS Cash Flow'!I27 -> 161073.21
A34: TOTAL EQUITY | B34: =SUM(B32:B33) -> 20000 | C34: =SUM(C32:C33) -> 36320.434 | D34: =SUM(D32:D33) -> 55163.996 | E34: =SUM(E32:E33) -> 76706.1 | F34: =SUM(F32:F33) -> 101132.41 | G34: =SUM(G32:G33) -> 127227.7 | H34: =SUM(H32:H33) -> 153870.98 | I34: =SUM(I32:I33) -> 181073.21
A36: TOTAL LIABILITIES & EQUITY | B36: =SUM(B25,B29,B34) -> 50000 | C36: =SUM(C25,C29,C34) -> 66320.434 | D36: =SUM(D25,D29,D34) -> 85163.996 | E36: =SUM(E25,E29,E34) -> 106706.1 | F36: =SUM(F25,F29,F34) -> 131132.41 | G36: =SUM(G25,G29,G34) -> 157227.7 | H36: =SUM(H25,H29,H34) -> 183870.98 | I36: =SUM(I25,I29,I34) -> 211073.21
A38: error check | B38: =B36-B18 -> 0 | C38: =C36-C18 -> 0 | D38: =D36-D18 -> 0 | E38: =E36-E18 -> 0 | F38: =F36-F18 -> 0 | G38: =G36-G18 -> 0 | H38: =H36-H18 -> 0 | I38: =I36-I18 -> 0

Sheet IS and Cash Flow
A1: Forecast Income Statement
C2: Forecast Period
A3: For the year ended | B3: 0 | C3: =B3+1 -> 1 | D3: =C3+1 -> 2 | E3: =D3+1 -> 3 | F3: =E3+1 -> 4 | G3: =F3+1 -> 5 | H3: =G3+1 -> 6 | I3: =H3+1 -> 7
A4: Total revenue | B4: 111754.8 | C4: =B4*(1+C5) -> 117342.54 | D4: =C4*(1+D5) -> 123209.67 | E4: =D4*(1+E5) -> 129370.15 | F4: =E4*(1+F5) -> 135838.66 | G4: =F4*(1+G5) -> 139913.82 | H4: =G4*(1+H5) -> 142712.09 | I4: =H4*(1+I5) -> 145566.34
A5: Revenue growth | C5: 0.05 | D5: 0.05 | E5: 0.05 | F5: 0.05 | G5: 0.03 | H5: 0.02 | I5: 0.02
A7: Operating expenses | B7: 91691.8 | C7: =B7*(1+C8) -> 94442.554 | D7: =C7*(1+D8) -> 97275.831 | E7: =D7*(1+E8) -> 100194.11 | F7: =E7*(1+F8) -> 103199.93 | G7: =F7*(1+G8) -> 105263.93 | H7: =G7*(1+H8) -> 107369.21 | I7: =H7*(1+I8) -> 109516.59
A8: Operating expense growth | C8: 0.03 | D8: 0.03 | E8: 0.03 | F8: 0.03 | G8: 0.02 | H8: 0.02 | I8: 0.02
A10: EBITDA | B10: =B4-B7 -> 20063 | C10: =C4-C7 -> 22899.986 | D10: =D4-D7 -> 25933.836 | E10: =E4-E7 -> 29176.045 | F10: =F4-F7 -> 32638.729 | G10: =G4-G7 -> 34649.89 | H10: =H4-H7 -> 35342.888 | I10: =I4-I7 -> 36049.746
A11: EBITDA margin | B11: =B10/B4 -> 0.17952696 | C11: =C10/C4 -> 0.19515502 | D11: =D10/D4 -> 0.2104854 | E11: =E10/E4 -> 0.22552378 | F11: =F10/F4 -> 0.2402757 | G11: =G10/G4 -> 0.24765167 | H11: =H10/H4 -> 0.24765167 | I11: =I10/I4 -> 0.24765167
A13: Depreciation & Amortization | B13: 2500 | C13: =C4*C14 -> 2625 | D13: =D4*D14 -> 2756.25 | E13: =E4*E14 -> 2894.0625 | F13: =F4*F14 -> 3038.7656 | G13: =G4*G14 -> 3129.9286 | H13: =H4*H14 -> 3192.5272 | I13: =I4*I14 -> 3256.3777
A14: D&A % of revenue | B14: =B13/B4 -> 0.022370404 | C14: =B14 -> 0.022370404 | D14: =C14 -> 0.022370404 | E14: =D14 -> 0.022370404 | F14: =E14 -> 0.022370404 | G14: =F14 -> 0.022370404 | H14: =G14 -> 0.022370404 | I14: =H14 -> 0.022370404
A16: EBIT | B16: =B10-B13 -> 17563 | C16: =C10-C13 -> 20274.986 | D16: =D10-D13 -> 23177.586 | E16: =E10-E13 -> 26281.982 | F16: =F10-F13 -> 29599.964 | G16: =G10-G13 -> 31519.962 | H16: =H10-H13 -> 32150.361 | I16: =I10-I13 -> 32793.368
A17: EBIT margin | B17: =B16/B4 -> 0.15715656 | C17: =C16/C4 -> 0.17278462 | D17: =D16/D4 -> 0.188115 | E17: =E16/E4 -> 0.20315337 | F17: =F16/F4 -> 0.2179053 | G17: =G16/G4 -> 0.22528126 | H17: =H16/H4 -> 0.22528126 | I17: =I16/I4 -> 0.22528126
A19: Interest | B19: 1500 | C19: ='[1]Bal Sheet'!B28*C20 -> 1500 | D19: ='[1]Bal Sheet'!C28*D20 -> 1500 | E19: ='[1]Bal Sheet'!D28*E20 -> 1500 | F19: ='[1]Bal Sheet'!E28*F20 -> 1500 | G19: ='[1]Bal Sheet'!F28*G20 -> 1500 | H19: ='[1]Bal Sheet'!G28*H20 -> 1500 | I19: ='[1]Bal Sheet'!H28*I20 -> 1500
A20: Interest rate | B20: =B19/'[1]Bal Sheet'!B28 -> 0.05 | C20: =B20 -> 0.05 | D20: =C20 -> 0.05 | E20: =D20 -> 0.05 | F20: =E20 -> 0.05 | G20: =F20 -> 0.05 | H20: =G20 -> 0.05 | I20: =H20 -> 0.05
A22: EBT | B22: =B16-B19 -> 16063 | C22: =C16-C19 -> 18774.986 | D22: =D16-D19 -> 21677.586 | E22: =E16-E19 -> 24781.982 | F22: =F16-F19 -> 28099.964 | G22: =G16-G19 -> 30019.962 | H22: =H16-H19 -> 30650.361 | I22: =I16-I19 -> 31293.368
A24: Tax | B24: 2100 | C24: =C22*C25 -> 2454.5521 | D24: =D22*D25 -> 2834.0242 | E24: =E22*E25 -> 3239.8782 | F24: =F22*F25 -> 3673.6552 | G24: =G22*G25 -> 3924.6666 | H24: =H22*H25 -> 4007.082 | I24: =I22*I25 -> 4091.1457
A25: Tax rate | B25: =B24/B22 -> 0.13073523 | C25: =B25 -> 0.13073523 | D25: =C25 -> 0.13073523 | E25: =D25 -> 0.13073523 | F25: =E25 -> 0.13073523 | G25: =F25 -> 0.13073523 | H25: =G25 -> 0.13073523 | I25: =H25 -> 0.13073523
A27: Net income | B27: =B22-B24 -> 13963 | C27: =C22-C24 -> 16320.434 | D27: =D22-D24 -> 18843.562 | E27: =E22-E24 -> 21542.104 | F27: =F22-F24 -> 24426.308 | G27: =G22-G24 -> 26095.295 | H27: =H22-H24 -> 26643.279 | I27: =I22-I24 -> 27202.222
A30: Forecast Cashflow
C31: Forecast Period
A32: For the year ended | C32: =B32+1 -> 1 | D32: =C32+1 -> 2 | E32: =D32+1 -> 3 | F32: =E32+1 -> 4 | G32: =F32+1 -> 5 | H32: =G32+1 -> 6 | I32: =H32+1 -> 7
A34: Net income | C34: =C27 -> 16320.434 | D34: =D27 -> 18843.562 | E34: =E27 -> 21542.104 | F34: =F27 -> 24426.308 | G34: =G27 -> 26095.295 | H34: =H27 -> 26643.279 | I34: =I27 -> 27202.222
A35: + D&A (non-cash) | C35: =C13 -> 2625 | D35: =D13 -> 2756.25 | E35: =E13 -> 2894.0625 | F35: =F13 -> 3038.7656 | G35: =G13 -> 3129.9286 | H35: =H13 -> 3192.5272 | I35: =I13 -> 3256.3777
A37: Changes in Net Working Capital
A38: - increase in inventory
A39: - increase in accounts receivable | C39: ='[1]Bal Sheet'!B8-'[1]Bal Sheet'!C8 -> -625 | D39: ='[1]Bal Sheet'!C8-'[1]Bal Sheet'!D8 -> -656.25 | E39: ='[1]Bal Sheet'!D8-'[1]Bal Sheet'!E8 -> -689.0625 | F39: ='[1]Bal Sheet'!E8-'[1]Bal Sheet'!F8 -> -723.51562 | G39: ='[1]Bal Sheet'!F8-'[1]Bal Sheet'!G8 -> -455.81484 | H39: ='[1]Bal Sheet'!G8-'[1]Bal Sheet'!H8 -> -312.99286 | I39: ='[1]Bal Sheet'!H8-'[1]Bal Sheet'!I8 -> -319.25272
A40: + increase in accounts payable | C40: ='[1]Bal Sheet'!C22-'[1]Bal Sheet'!B22 -> 0 | D40: ='[1]Bal Sheet'!D22-'[1]Bal Sheet'!C22 -> 0 | E40: ='[1]Bal Sheet'!E22-'[1]Bal Sheet'!D22 -> 0 | F40: ='[1]Bal Sheet'!F22-'[1]Bal Sheet'!E22 -> 0 | G40: ='[1]Bal Sheet'!G22-'[1]Bal Sheet'!F22 -> 0 | H40: ='[1]Bal Sheet'!H22-'[1]Bal Sheet'!G22 -> 0 | I40: ='[1]Bal Sheet'!I22-'[1]Bal Sheet'!H22 -> 0
A42: Cash flow from operations | C42: =SUM(C34:C40) -> 18320.434 | D42: =SUM(D34:D40) -> 20943.562 | E42: =SUM(E34:E40) -> 23747.104 | F42: =SUM(F34:F40) -> 26741.558 | G42: =SUM(G34:G40) -> 28769.409 | H42: =SUM(H34:H40) -> 29522.813 | I42: =SUM(I34:I40) -> 30139.347
A45: Capital expenditures | C45: =-C4*C46 -> -8213.9778 | D45: =-D4*D46 -> -8624.6767 | E45: =-E4*E46 -> -9055.9105 | F45: =-F4*F46 -> -9508.7061 | G45: =-G4*G46 -> -9793.9672 | H45: =-H4*H46 -> -9989.8466 | I45: =-I4*I46 -> -10189.644
A46: Capex % of revenue | C46: 0.07 | D46: 0.07 | E46: 0.07 | F46: 0.07 | G46: 0.07 | H46: 0.07 | I46: 0.07
A48: Cash flow from investment | C48: =SUM(C45) -> -8213.9778 | D48: =SUM(D45) -> -8624.6767 | E48: =SUM(E45) -> -9055.9105 | F48: =SUM(F45) -> -9508.7061 | G48: =SUM(G45) -> -9793.9672 | H48: =SUM(H45) -> -9989.8466 | I48: =SUM(I45) -> -10189.644
A51: Debt paydown | C51: 0 | D51: 0 | E51: 0 | F51: 0 | G51: 0 | H51: 0 | I51: 0
A52: Debt borrowings | C52: 0 | D52: 0 | E52: 0 | F52: 0 | G52: 0 | H52: 0 | I52: 0
A53: Cash flow from Financing | C53: =SUM(C51:C52) -> 0 | D53: =SUM(D51:D52) -> 0 | E53: =SUM(E51:E52) -> 0 | F53: =SUM(F51:F52) -> 0 | G53: =SUM(G51:G52) -> 0 | H53: =SUM(H51:H52) -> 0 | I53: =SUM(I51:I52) -> 0
A55: Beginning Cash Balance | C55: ='[1]Bal Sheet'!B6 -> 7500 | D55: =C57 -> 17606.456 | E55: =D57 -> 29925.342 | F55: =E57 -> 44616.535 | G55: =F57 -> 61849.387 | H55: =G57 -> 80824.829 | I55: =H57 -> 100357.8
A56: Net Cash Flow | C56: =C42+C48+C53 -> 10106.456 | D56: =D42+D48+D53 -> 12318.885 | E56: =E42+E48+E53 -> 14691.194 | F56: =F42+F48+F53 -> 17232.852 | G56: =G42+G48+G53 -> 18975.442 | H56: =H42+H48+H53 -> 19532.967 | I56: =I42+I48+I53 -> 19949.704
A57: Ending Cash Balance | C57: =C55+C56 -> 17606.456 | D57: =D55+D56 -> 29925.342 | E57: =E55+E56 -> 44616.535 | F57: =F55+F56 -> 61849.387 | G57: =G55+G56 -> 80824.829 | H57: =H55+H56 -> 100357.8 | I57: =I55+I56 -> 120307.5

Sheet DCF
A1: Capital Structure
B2: Debt | C2: Equity
A3: $ amount | B3: ='Balance Sheet'!B29 -> 30000 | C3: ='Balance Sheet'!C34 -> 36320.434
A4: % of capital structure | B4: =B3/SUM($B$3:$C$3) -> 0.45234927 | C4: =C3/SUM($B$3:$C$3) -> 0.54765073
A5: Cost of capital (net of tax) | B5: ='IS and Cash Flow'!C20*(1-'IS and Cash Flow'!C25) -> 0.043463238 | C5: 0.15
A6: Weighted Average Cost of Capital (WACC) | B6: =(B4*B5)+(C4*C5) -> 0.10180817
A8: Perpetuity Growth Rate | B8: 0.02
A10: Discounted Cash Flow Valuation
A11: Forcast Period -> | B11: Year 0 | C11: Year 1 | D11: Year 2 | E11: Year 3 | F11: Year 4 | G11: Year 5 | H11: Year 6 | I11: Year 7
A13: Net Income | C13: ='IS and Cash Flow'!C27 -> 16320.434 | D13: ='IS and Cash Flow'!D27 -> 18843.562 | E13: ='IS and Cash Flow'!E27 -> 21542.104 | F13: ='IS and Cash Flow'!F27 -> 24426.308 | G13: ='IS and Cash Flow'!G27 -> 26095.295 | H13: ='IS and Cash Flow'!H27 -> 26643.279 | I13: ='IS and Cash Flow'!I27 -> 27202.222
A14: "+" D&A and other noncash charges | C14: ='IS and Cash Flow'!C13 -> 2625 | D14: ='IS and Cash Flow'!D13 -> 2756.25 | E14: ='IS and Cash Flow'!E13 -> 2894.0625 | F14: ='IS and Cash Flow'!F13 -> 3038.7656 | G14: ='IS and Cash Flow'!G13 -> 3129.9286 | H14: ='IS and Cash Flow'!H13 -> 3192.5272 | I14: ='IS and Cash Flow'!I13 -> 3256.3777
A15: "+" Interest*(1-tax rate) | C15: ='IS and Cash Flow'!C19*(1-'IS and Cash Flow'!C25) -> 1303.8972 | D15: ='IS and Cash Flow'!D19*(1-'IS and Cash Flow'!D25) -> 1303.8972 | E15: ='IS and Cash Flow'!E19*(1-'IS and Cash Flow'!E25) -> 1303.8972 | F15: ='IS and Cash Flow'!F19*(1-'IS and Cash Flow'!F25) -> 1303.8972 | G15: ='IS and Cash Flow'!G19*(1-'IS and Cash Flow'!G25) -> 1303.8972 | H15: ='IS and Cash Flow'!H19*(1-'IS and Cash Flow'!H25) -> 1303.8972 | I15: ='IS and Cash Flow'!I19*(1-'IS and Cash Flow'!I25) -> 1303.8972
A16: "-" Capital expenditures | C16: ='IS and Cash Flow'!C45 -> -8213.9778 | D16: ='IS and Cash Flow'!D45 -> -8624.6767 | E16: ='IS and Cash Flow'!E45 -> -9055.9105 | F16: ='IS and Cash Flow'!F45 -> -9508.7061 | G16: ='IS and Cash Flow'!G45 -> -9793.9672 | H16: ='IS and Cash Flow'!H45 -> -9989.8466 | I16: ='IS and Cash Flow'!I45 -> -10189.644
A17: "+" Change in Working Capital | C17: =SUM('IS and Cash Flow'!C38:C40) -> -625 | D17: =SUM('IS and Cash Flow'!D38:D40) -> -656.25 | E17: =SUM('IS and Cash Flow'!E38:E40) -> -689.0625 | F17: =SUM('IS and Cash Flow'!F38:F40) -> -723.51562 | G17: =SUM('IS and Cash Flow'!G38:G40) -> -455.81484 | H17: =SUM('IS and Cash Flow'!H38:H40) -> -312.99286 | I17: =SUM('IS and Cash Flow'!I38:I40) -> -319.25272
A18: Free Cash Flow to Firm | C18: =SUM(C13:C17) -> 11410.353 | D18: =SUM(D13:D17) -> 13622.783 | E18: =SUM(E13:E17) -> 15995.091 | F18: =SUM(F13:F17) -> 18536.749 | G18: =SUM(G13:G17) -> 20279.339 | H18: =SUM(H13:H17) -> 20836.864 | I18: =SUM(I13:I17) -> 21253.601
A19: Terminal Value | I19: =I18*(1+B8)/(B6-B8) -> 264993.98
A20: Total cash flow to discount | C20: =SUM(C18:C19) -> 11410.353 | D20: =SUM(D18:D19) -> 13622.783 | E20: =SUM(E18:E19) -> 15995.091 | F20: =SUM(F18:F19) -> 18536.749 | G20: =SUM(G18:G19) -> 20279.339 | H20: =SUM(H18:H19) -> 20836.864 | I20: =SUM(I18:I19) -> 286247.58
A22: Enterprise Value (NPV of cash flows to firm) | B22: =NPV(B6,C20:I20) -> 215460.37
A23: "+" Cash | B23: ='Balance Sheet'!B6 -> 7500
A24: "-" Debt | B24: =-'Balance Sheet'!B28 -> -30000
A25: Equity Value | B25: =SUM(B22:B24) -> 192960.37
A27: Shares Outstanding | B27: 5000
A28: Fair value per share | B28: =B25/B27 -> 38.592073
