Workbook

Sheet Zenith Cafe
A2: Zenith Café
A6: Financial Modelling 2025
A7: About the project
A11: Content
A12: Balance Sheet | B12: BS
A13: Assumptions | B13: Assumptions
A14: Revenue | B14: Revenue
A15: Expenses | B15: Expenses
A16: IS | B16: Income Statement
A17: Cash Flow | B17: Cash Flow

Sheet Assumptions
A1: Sales Estimation - Senarios
A2: Home
B3: Worst | C3: Base | D3: Best
A4: Cups per day | B4: 100 | C4: 120 | D4: 140
A5: Rent | B5: 1320 | C5: 1200 | D5: 1080
A8: Assumptions
A9: Revenue
A11: Avg no cups sold per day | B11: =HLOOKUP('Income St'!$B$1,B3:D4,2,0) -> 100
B15: % of units | C15: Price
A16: Large | B16: 0.4 | C16: 4
A17: Small | B17: 0.6 | C17: 3.5
A20: Expenses Assumptions
A22: Consumables per cup | B22: 0.45
A23: Consumables have been calculated on average for large and small cups
A25: Basic Salary | B25: 50000
A26: Other staff costs and benefits | B26: 0.25
A28: Monthly Rent | B28: 1200
A29: Monthly Utilities | B29: 100
A31: Interest rate | B31: 0.07
A32: Income Tax | B32: 0.3
A33: All GST, VAT or sales tax is excluded for the purposes of this model
A36: Other Assumptions
B38: Jan | C38: Feb | D38: Mar | E38: Apr | F38: May | G38: Jun | H38: Jul | I38: Aug | J38: Sept | K38: Oct | L38: Nov | M38: Dec
A39: Number of business days per month | B39: 22 | C39: 20 | D39: 22 | E39: 18 | F39: 23 | G39: 21 | H39: 22 | I39: 22 | J39: 20 | K39: 20 | L39: 22 | M39: 19
A40: Based on past year calender
A41: Seasonality variance (% of an avg) | B41: 0.8 | C41: 0.9 | D41: 1 | E41: 1 | F41: 1.1 | G41: 1.2 | H41: 1.2 | I41: 1.1 | J41: 1 | K41: 1 | L41: 0.9 | M41: 0.8
A42: Based on historical demand data

Sheet Revenue
A1: Revenue | B1: Home
B3: Jan | C3: Feb | D3: Mar | E3: Apr | F3: May | G3: Jun | H3: Jul | I3: Aug | J3: Sept | K3: Oct | L3: Nov | M3: Dec
A4: Unit Sales Forecast
A5: Cups of coffee sold per day | B5: =Assumptions!$B$11*Assumptions!B41 -> 80 | C5: =Assumptions!$B$11*Assumptions!C41 -> 90 | D5: =Assumptions!$B$11*Assumptions!D41 -> 100 | E5: =Assumptions!$B$11*Assumptions!E41 -> 100 | F5: =Assumptions!$B$11*Assumptions!F41 -> 110 | G5: =Assumptions!$B$11*Assumptions!G41 -> 120 | H5: =Assumptions!$B$11*Assumptions!H41 -> 120 | I5: =Assumptions!$B$11*Assumptions!I41 -> 110 | ... M5: =Assumptions!$B$11*Assumptions!M41 -> 80
A6: Large | B6: =Assumptions!$B$16*Revenue!B5 -> 32 | C6: =Assumptions!$B$16*Revenue!C5 -> 36 | D6: =Assumptions!$B$16*Revenue!D5 -> 40 | E6: =Assumptions!$B$16*Revenue!E5 -> 40 | F6: =Assumptions!$B$16*Revenue!F5 -> 44 | G6: =Assumptions!$B$16*Revenue!G5 -> 48 | H6: =Assumptions!$B$16*Revenue!H5 -> 48 | I6: =Assumptions!$B$16*Revenue!I5 -> 44 | ... M6: =Assumptions!$B$16*Revenue!M5 -> 32
A7: Small | B7: =Assumptions!$B$17*Revenue!B5 -> 48 | C7: =Assumptions!$B$17*Revenue!C5 -> 54 | D7: =Assumptions!$B$17*Revenue!D5 -> 60 | E7: =Assumptions!$B$17*Revenue!E5 -> 60 | F7: =Assumptions!$B$17*Revenue!F5 -> 66 | G7: =Assumptions!$B$17*Revenue!G5 -> 72 | H7: =Assumptions!$B$17*Revenue!H5 -> 72 | I7: =Assumptions!$B$17*Revenue!I5 -> 66 | ... M7: =Assumptions!$B$17*Revenue!M5 -> 48
A8: Total | B8: =SUM(B6:B7) -> 80 | C8: =SUM(C6:C7) -> 90 | D8: =SUM(D6:D7) -> 100 | E8: =SUM(E6:E7) -> 100 | F8: =SUM(F6:F7) -> 110 | G8: =SUM(G6:G7) -> 120 | H8: =SUM(H6:H7) -> 120 | I8: =SUM(I6:I7) -> 110 | ... M8: =SUM(M6:M7) -> 80
A9: error check | B9: =B8-B5 -> 0 | C9: =C8-C5 -> 0 | D9: =D8-D5 -> 0 | E9: =E8-E5 -> 0 | F9: =F8-F5 -> 0 | G9: =G8-G5 -> 0 | H9: =H8-H5 -> 0 | I9: =I8-I5 -> 0 | ... M9: =M8-M5 -> 0
A11: # Sales Forcast
A12: Large sales per day | B12: =B6*Assumptions!$C$16 -> 128 | C12: =C6*Assumptions!$C$16 -> 144 | D12: =D6*Assumptions!$C$16 -> 160 | E12: =E6*Assumptions!$C$16 -> 160 | F12: =F6*Assumptions!$C$16 -> 176 | G12: =G6*Assumptions!$C$16 -> 192 | H12: =H6*Assumptions!$C$16 -> 192 | I12: =I6*Assumptions!$C$16 -> 176 | ... M12: =M6*Assumptions!$C$16 -> 128
A13: Small sales per day | B13: =B7*Assumptions!$C$17 -> 168 | C13: =C7*Assumptions!$C$17 -> 189 | D13: =D7*Assumptions!$C$17 -> 210 | E13: =E7*Assumptions!$C$17 -> 210 | F13: =F7*Assumptions!$C$17 -> 231 | G13: =G7*Assumptions!$C$17 -> 252 | H13: =H7*Assumptions!$C$17 -> 252 | I13: =I7*Assumptions!$C$17 -> 231 | ... M13: =M7*Assumptions!$C$17 -> 168
A14: Daily Sales | B14: =SUM(B12:B13) -> 296 | C14: =SUM(C12:C13) -> 333 | D14: =SUM(D12:D13) -> 370 | E14: =SUM(E12:E13) -> 370 | F14: =SUM(F12:F13) -> 407 | G14: =SUM(G12:G13) -> 444 | H14: =SUM(H12:H13) -> 444 | I14: =SUM(I12:I13) -> 407 | ... M14: =SUM(M12:M13) -> 296
A15: Monthly Sales | B15: =B14*Assumptions!B39 -> 6512 | C15: =C14*Assumptions!C39 -> 6660 | D15: =D14*Assumptions!D39 -> 8140 | E15: =E14*Assumptions!E39 -> 6660 | F15: =F14*Assumptions!F39 -> 9361 | G15: =G14*Assumptions!G39 -> 9324 | H15: =H14*Assumptions!H39 -> 9768 | I15: =I14*Assumptions!I39 -> 8954 | ... M15: =M14*Assumptions!M39 -> 5624

Sheet Expenses
A1: Expenses | B1: Home
B3: Jan | C3: Feb | D3: Mar | E3: Apr | F3: May | G3: Jun | H3: Jul | I3: Aug | J3: Sept | K3: Oct | L3: Nov | M3: Dec
A4: Staff Costs
A5: Barista Salary | B5: =Assumptions!$B$25/12 -> 4166.6667 | C5: =Assumptions!$B$25/12 -> 4166.6667 | D5: =Assumptions!$B$25/12 -> 4166.6667 | E5: =Assumptions!$B$25/12 -> 4166.6667 | F5: =Assumptions!$B$25/12 -> 4166.6667 | G5: =Assumptions!$B$25/12 -> 4166.6667 | H5: =Assumptions!$B$25/12 -> 4166.6667 | I5: =Assumptions!$B$25/12 -> 4166.6667 | ... M5: =Assumptions!$B$25/12 -> 4166.6667
A6: Other staff costs and benefits | B6: =B5*Assumptions!$B$26 -> 1041.6667 | C6: =C5*Assumptions!$B$26 -> 1041.6667 | D6: =D5*Assumptions!$B$26 -> 1041.6667 | E6: =E5*Assumptions!$B$26 -> 1041.6667 | F6: =F5*Assumptions!$B$26 -> 1041.6667 | G6: =G5*Assumptions!$B$26 -> 1041.6667 | H6: =H5*Assumptions!$B$26 -> 1041.6667 | I6: =I5*Assumptions!$B$26 -> 1041.6667 | ... M6: =M5*Assumptions!$B$26 -> 1041.6667
A7: Total staff costs | B7: =SUM(B5:B6) -> 5208.3333 | C7: =SUM(C5:C6) -> 5208.3333 | D7: =SUM(D5:D6) -> 5208.3333 | E7: =SUM(E5:E6) -> 5208.3333 | F7: =SUM(F5:F6) -> 5208.3333 | G7: =SUM(G5:G6) -> 5208.3333 | H7: =SUM(H5:H6) -> 5208.3333 | I7: =SUM(I5:I6) -> 5208.3333 | ... M7: =SUM(M5:M6) -> 5208.3333
A9: Other Costs
A10: Rent | B10: =Assumptions!$B$28 -> 1200 | C10: =Assumptions!$B$28 -> 1200 | D10: =Assumptions!$B$28 -> 1200 | E10: =Assumptions!$B$28 -> 1200 | F10: =Assumptions!$B$28 -> 1200 | G10: =Assumptions!$B$28 -> 1200 | H10: =Assumptions!$B$28 -> 1200 | I10: =Assumptions!$B$28 -> 1200 | ... M10: =Assumptions!$B$28 -> 1200
A11: Utilities | B11: =Assumptions!$B$29 -> 100 | C11: =Assumptions!$B$29 -> 100 | D11: =Assumptions!$B$29 -> 100 | E11: =Assumptions!$B$29 -> 100 | F11: =Assumptions!$B$29 -> 100 | G11: =Assumptions!$B$29 -> 100 | H11: =Assumptions!$B$29 -> 100 | I11: =Assumptions!$B$29 -> 100 | ... M11: =Assumptions!$B$29 -> 100
A12: Consumables | B12: =Revenue!B5*Assumptions!B39*Assumptions!$B$22 -> 792 | C12: =Revenue!C5*Assumptions!C39*Assumptions!$B$22 -> 810 | D12: =Revenue!D5*Assumptions!D39*Assumptions!$B$22 -> 990 | E12: =Revenue!E5*Assumptions!E39*Assumptions!$B$22 -> 810 | F12: =Revenue!F5*Assumptions!F39*Assumptions!$B$22 -> 1138.5 | G12: =Revenue!G5*Assumptions!G39*Assumptions!$B$22 -> 1134 | H12: =Revenue!H5*Assumptions!H39*Assumptions!$B$22 -> 1188 | I12: =Revenue!I5*Assumptions!I39*Assumptions!$B$22 -> 1089 | ... M12: =Revenue!M5*Assumptions!M39*Assumptions!$B$22 -> 684
A13: Total other costs | B13: =SUM(B10:B12) -> 2092 | C13: =SUM(C10:C12) -> 2110 | D13: =SUM(D10:D12) -> 2290 | E13: =SUM(E10:E12) -> 2110 | F13: =SUM(F10:F12) -> 2438.5 | G13: =SUM(G10:G12) -> 2434 | H13: =SUM(H10:H12) -> 2488 | I13: =SUM(I10:I12) -> 2389 | ... M13: =SUM(M10:M12) -> 1984
A15: Total costs | B15: =SUM(B7,B13) -> 7300.3333 | C15: =SUM(C7,C13) -> 7318.3333 | D15: =SUM(D7,D13) -> 7498.3333 | E15: =SUM(E7,E13) -> 7318.3333 | F15: =SUM(F7,F13) -> 7646.8333 | G15: =SUM(G7,G13) -> 7642.3333 | H15: =SUM(H7,H13) -> 7696.3333 | I15: =SUM(I7,I13) -> 7597.3333 | ... M15: =SUM(M7,M13) -> 7192.3333
A18: Depreciation $ Amortization (D&A) Schedule
A20: Purchase PriceUSeful Life | B20: Purchase Cost | C20: Lifespan | D20: Jan | E20: Feb | F20: Mar | G20: Apr | H20: May | I20: Jun | J20: Jul | K20: Aug | L20: Sept | M20: Oct | N20: Nov | O20: Dec
A21: Coffee Machine | B21: ='Balance Sheet'!F11 -> 10000 | C21: 3 | D21: =$B$21/$C$21/12 -> 277.77778 | E21: =$B$21/$C$21/12 -> 277.77778 | F21: =$B$21/$C$21/12 -> 277.77778 | G21: =$B$21/$C$21/12 -> 277.77778 | H21: =$B$21/$C$21/12 -> 277.77778 | I21: =$B$21/$C$21/12 -> 277.77778 | J21: =$B$21/$C$21/12 -> 277.77778 | K21: =$B$21/$C$21/12 -> 277.77778 | ... O21: =$B$21/$C$21/12 -> 277.77778
A22: Furniture & Fixture | B22: ='Balance Sheet'!F12 -> 35000 | C22: 10 | D22: =$B$22/10/12 -> 291.66667 | E22: =$B$22/10/12 -> 291.66667 | F22: =$B$22/10/12 -> 291.66667 | G22: =$B$22/10/12 -> 291.66667 | H22: =$B$22/10/12 -> 291.66667 | I22: =$B$22/10/12 -> 291.66667 | J22: =$B$22/10/12 -> 291.66667 | K22: =$B$22/10/12 -> 291.66667 | ... O22: =$B$22/10/12 -> 291.66667
A23: Total D&A expense | D23: =SUM(D21,D22) -> 569.44444 | E23: =SUM(E21,E22) -> 569.44444 | F23: =SUM(F21,F22) -> 569.44444 | G23: =SUM(G21,G22) -> 569.44444 | H23: =SUM(H21,H22) -> 569.44444 | I23: =SUM(I21,I22) -> 569.44444 | J23: =SUM(J21,J22) -> 569.44444 | K23: =SUM(K21,K22) -> 569.44444 | ... O23: =SUM(O21,O22) -> 569.44444

Sheet Balance Sheet
A1: Balance Sheet | B1: Home
A2: end of | B2: Year 0 | C2: Year 1 | E2: Sources of Funds
A3: ASSETS | E3: Borrowed from the Bank | F3: 30000
A4: Current Assets | E4: Equity raised | F4: 25000
A5: Cash at Bank | B5: ='Cash Flow'!C4 -> 5000 | C5: ='Cash Flow'!N20 -> 8171.75 | E5: Total funds sourced | F5: =SUM(F3:F4) -> 55000
A6: Investory | B6: ='Balance Sheet'!F10 -> 5000 | C6: =B6-SUM('Cash Flow'!C8:N8) -> 5000
A7: Account Receivable
A8: Total Current Assets | B8: =SUM(B5:B7) -> 10000 | C8: =SUM(C5:C7) -> 13171.75 | E8: Uses of Funds
E9: Working Cash | F9: 5000
A10: Fixed Assets | E10: Working Inventory | F10: 5000
A11: Gross PP&E | B11: =SUM(F11,F12) -> 45000 | C11: =B11-SUM('Cash Flow'!C13:N13) -> 45000 | E11: Coffee Machine | F11: 10000
A12: Less: Depreciation & Amortization | C12: =-'Income St'!O13 -> -6833.3333 | E12: Furniture & Fixtures | F12: 35000
A13: Total Current Assets | B13: =SUM(B11:B12) -> 45000 | C13: =SUM(C11:C12) -> 38166.667 | E13: Total funds used | F13: =SUM(F9:F12) -> 55000
A15: TOTAL ASSETS | B15: =SUM(B13,B8) -> 55000 | C15: =SUM(C13,C8) -> 51338.417
A17: LIABILITIES
A18: Current Liabilities
A19: Account Payable
A20: Total Current Liabilities
A22: Long Term Liabilities
A23: Bank Loan | B23: =F3 -> 30000 | C23: =F3 -> 30000
A24: Total Current Liabilities | B24: =SUM(B23) -> 30000 | C24: =SUM(C23) -> 30000
A26: EQUITY
A27: Owner's Funds | B27: =F4 -> 25000 | C27: =F4 -> 25000
A28: Retained Earnings | C28: ='Income St'!O20 -> -3661.5833
A29: Total Equity | B29: =SUM(B27:B28) -> 25000 | C29: =SUM(C27:C28) -> 21338.417
A31: TOTAL LIABILITIES & EQUITY | B31: =SUM(B29,B24) -> 55000 | C31: =SUM(C29,C24) -> 51338.417
A32: error check | B32: =B31-B15 -> 0 | C32: =C31-C15 -> 0

Sheet Cash Flow
A1: Forcast Cashflow | B1: Home
A2: ='Income St'!$B$1 -> Worst
B3: Pre-Open | C3: Jan | D3: Feb | E3: Mar | F3: Apr | G3: May | H3: Jun | I3: Jul | J3: Aug | K3: Sept | L3: Oct | M3: Nov | N3: Dec
A4: Opening Cash | C4: =B20 -> 5000 | D4: =C20 -> 4496.5 | E4: =D20 -> 4084 | F4: =E20 -> 4581.5 | G4: =F20 -> 4169 | H4: =G20 -> 5417.25 | I4: =H20 -> 6642.75 | J4: =I20 -> 8141.25 | ... N4: =M20 -> 9221.25
A5: Cash flow from Operations
A6: Net Income | C6: ='Income St'!C20 -> -1072.9444 | D6: ='Income St'!D20 -> -981.94444 | E6: ='Income St'!E20 -> -71.944444 | F6: ='Income St'!F20 -> -981.94444 | G6: ='Income St'!G20 -> 678.80556 | H6: ='Income St'!H20 -> 656.05556 | I6: ='Income St'!I20 -> 929.05556 | J6: ='Income St'!J20 -> 428.55556 | ... N6: ='Income St'!N20 -> -1618.9444
A7: "+" D&A (non-cash) | C7: =Expenses!D23 -> 569.44444 | D7: =Expenses!E23 -> 569.44444 | E7: =Expenses!F23 -> 569.44444 | F7: =Expenses!G23 -> 569.44444 | G7: =Expenses!H23 -> 569.44444 | H7: =Expenses!I23 -> 569.44444 | I7: =Expenses!J23 -> 569.44444 | J7: =Expenses!K23 -> 569.44444 | ... N7: =Expenses!O23 -> 569.44444
A8: "-" Increase in inventory | B8: =-'Balance Sheet'!F10 -> -5000
A9: "-" Increase in account receivable
A10: "+" Increase in account payable
A12: Cash flow from Investment
A13: Capital expenditure | B13: =-'Balance Sheet'!F11-'Balance Sheet'!F12 -> -45000
A15: Cash flow from Financing
A16: Bank loan | B16: ='Balance Sheet'!F3 -> 30000
A17: Capital raised | B17: ='Balance Sheet'!F4 -> 25000
A18: Paydown of Debt
A20: Closing Cash | B20: =SUM(B4:B19) -> 5000 | C20: =SUM(C4:C19) -> 4496.5 | D20: =SUM(D4:D19) -> 4084 | E20: =SUM(E4:E19) -> 4581.5 | F20: =SUM(F4:F19) -> 4169 | G20: =SUM(G4:G19) -> 5417.25 | H20: =SUM(H4:H19) -> 6642.75 | I20: =SUM(I4:I19) -> 8141.25 | ... N20: =SUM(N4:N19) -> 8171.75

Sheet Income St
A1: Scenario: | B1: Worst | G1: Home
A2: Income Statement - Scenario
A3: Forcast Income Statement
C4: Jan | D4: Feb | E4: Mar | F4: Apr | G4: May | H4: Jun | I4: Jul | J4: Aug | K4: Sept | L4: Oct | M4: Nov | N4: Dec | O4: Total
A5: Revenue | C5: =Revenue!B15 -> 6512 | D5: =Revenue!C15 -> 6660 | E5: =Revenue!D15 -> 8140 | F5: =Revenue!E15 -> 6660 | G5: =Revenue!F15 -> 9361 | H5: =Revenue!G15 -> 9324 | I5: =Revenue!H15 -> 9768 | J5: =Revenue!I15 -> 8954 | ... N5: =Revenue!M15 -> 5624 | O5: =SUM(C5:N5) -> 93129
A7: Staff Costs | C7: =Expenses!B7 -> 5208.3333 | D7: =Expenses!C7 -> 5208.3333 | E7: =Expenses!D7 -> 5208.3333 | F7: =Expenses!E7 -> 5208.3333 | G7: =Expenses!F7 -> 5208.3333 | H7: =Expenses!G7 -> 5208.3333 | I7: =Expenses!H7 -> 5208.3333 | J7: =Expenses!I7 -> 5208.3333 | ... N7: =Expenses!M7 -> 5208.3333 | O7: =SUM(C7:N7) -> 62500
A8: Other Costs | C8: =Expenses!B13 -> 2092 | D8: =Expenses!C13 -> 2110 | E8: =Expenses!D13 -> 2290 | F8: =Expenses!E13 -> 2110 | G8: =Expenses!F13 -> 2438.5 | H8: =Expenses!G13 -> 2434 | I8: =Expenses!H13 -> 2488 | J8: =Expenses!I13 -> 2389 | ... N8: =Expenses!M13 -> 1984 | O8: =SUM(C8:N8) -> 26926.5
A9: Total Expenses | C9: =SUM(C7:C8) -> 7300.3333 | D9: =SUM(D7:D8) -> 7318.3333 | E9: =SUM(E7:E8) -> 7498.3333 | F9: =SUM(F7:F8) -> 7318.3333 | G9: =SUM(G7:G8) -> 7646.8333 | H9: =SUM(H7:H8) -> 7642.3333 | I9: =SUM(I7:I8) -> 7696.3333 | J9: =SUM(J7:J8) -> 7597.3333 | ... N9: =SUM(N7:N8) -> 7192.3333 | O9: =SUM(C9:N9) -> 89426.5
A11: EBITDA | C11: =C5-C9 -> -788.33333 | D11: =D5-D9 -> -658.33333 | E11: =E5-E9 -> 641.66667 | F11: =F5-F9 -> -658.33333 | G11: =G5-G9 -> 1714.1667 | H11: =H5-H9 -> 1681.6667 | I11: =I5-I9 -> 2071.6667 | J11: =J5-J9 -> 1356.6667 | ... N11: =N5-N9 -> -1568.3333 | O11: =SUM(C11:N11) -> 3702.5
A13: Depreciation & Amorization (D&A) Expenses | C13: =Expenses!D23 -> 569.44444 | D13: =Expenses!E23 -> 569.44444 | E13: =Expenses!F23 -> 569.44444 | F13: =Expenses!G23 -> 569.44444 | G13: =Expenses!H23 -> 569.44444 | H13: =Expenses!I23 -> 569.44444 | I13: =Expenses!J23 -> 569.44444 | J13: =Expenses!K23 -> 569.44444 | ... N13: =Expenses!O23 -> 569.44444 | O13: =SUM(C13:N13) -> 6833.3333
A14: EBIT | C14: =C11-C13 -> -1357.7778 | D14: =D11-D13 -> -1227.7778 | E14: =E11-E13 -> 72.222222 | F14: =F11-F13 -> -1227.7778 | G14: =G11-G13 -> 1144.7222 | H14: =H11-H13 -> 1112.2222 | I14: =I11-I13 -> 1502.2222 | J14: =J11-J13 -> 787.22222 | ... N14: =N11-N13 -> -2137.7778 | O14: =SUM(C14:N14) -> -3130.8333
A16: Interest | C16: ='Balance Sheet'!$F$3*Assumptions!$B$31/12 -> 175 | D16: ='Balance Sheet'!$F$3*Assumptions!$B$31/12 -> 175 | E16: ='Balance Sheet'!$F$3*Assumptions!$B$31/12 -> 175 | F16: ='Balance Sheet'!$F$3*Assumptions!$B$31/12 -> 175 | G16: ='Balance Sheet'!$F$3*Assumptions!$B$31/12 -> 175 | H16: ='Balance Sheet'!$F$3*Assumptions!$B$31/12 -> 175 | I16: ='Balance Sheet'!$F$3*Assumptions!$B$31/12 -> 175 | J16: ='Balance Sheet'!$F$3*Assumptions!$B$31/12 -> 175 | ... N16: ='Balance Sheet'!$F$3*Assumptions!$B$31/12 -> 175 | O16: =SUM(C16:N16) -> 2100
A17: EBT | C17: =C14-C16 -> -1532.7778 | D17: =D14-D16 -> -1402.7778 | E17: =E14-E16 -> -102.77778 | F17: =F14-F16 -> -1402.7778 | G17: =G14-G16 -> 969.72222 | H17: =H14-H16 -> 937.22222 | I17: =I14-I16 -> 1327.2222 | J17: =J14-J16 -> 612.22222 | ... N17: =N14-N16 -> -2312.7778 | O17: =SUM(C17:N17) -> -5230.8333
A19: Tax | C19: =C17*Assumptions!$B$32 -> -459.83333 | D19: =D17*Assumptions!$B$32 -> -420.83333 | E19: =E17*Assumptions!$B$32 -> -30.833333 | F19: =F17*Assumptions!$B$32 -> -420.83333 | G19: =G17*Assumptions!$B$32 -> 290.91667 | H19: =H17*Assumptions!$B$32 -> 281.16667 | I19: =I17*Assumptions!$B$32 -> 398.16667 | J19: =J17*Assumptions!$B$32 -> 183.66667 | ... N19: =N17*Assumptions!$B$32 -> -693.83333 | O19: =SUM(C19:N19) -> -1569.25
A20: Net Income | C20: =C17-C19 -> -1072.9444 | D20: =D17-D19 -> -981.94444 | E20: =E17-E19 -> -71.944444 | F20: =F17-F19 -> -981.94444 | G20: =G17-G19 -> 678.80556 | H20: =H17-H19 -> 656.05556 | I20: =I17-I19 -> 929.05556 | J20: =J17-J19 -> 428.55556 | ... N20: =N17-N19 -> -1618.9444 | O20: =SUM(C20:N20) -> -3661.5833
